{
  "ranking_parameters": [
    {
      "id": "1",
      "name": "google",
      "priority": [
        {
          "references": true,
          "seniurity": 5,
          "keywords": 2
        }
      ],
      "grade_per_unit": 30,
      "date_created": "16/01/2024"
    },
    {
      "id": "2",
      "name": "facebook",
      "priority": [
        {
          "references": false,
          "seniurity": 5,
          "keywords": 2
        }
      ],
      "grade_per_unit": 15,
      "date_created": "16/01/2024"
    }
  ],
  "search_engine_ranking": [
    {
      "id": "1",
      "website_product_rel_id": "123",
      "name": "google",
      "parameter_id": 1,
      "parameter_value": "55",
      "parameter_grade": "80",
      "date_created": "16/01/2024"
    },
    {
      "id": "2",
      "website_product_rel_id": "654",
      "name": "facebook",
      "parameter_id": 1,
      "parameter_value": "150",
      "parameter_grade": "100",
      "date_created": "20/01/2024"
    }
  ],
  "websites_products": [
    {
      "id": "1",
      "website_id": 1,
      "product_id": 101,
      "references": true,
      "product_page_unique_url": "https://google.com",
      "date_created": "15/10/2023"
    },
    {
      "id": "2",
      "website_id": 2,
      "product_id": 102,
      "references": false,
      "product_page_unique_url": "https://facebook.com",
      "date_created": "01/12/2023"
    }
  ],
  "websites": [
    {
      "id": "1",
      "URL": "https://example1.com",
      "date_created": "15/10/2023",
      "reference": "www.referenced_site.com"
    },
    {
      "id": "2",
      "URL": "https://example2.com",
      "date_created": "01/12/2023"
    },
    {
      "id": "3",
      "URL": "https://example3.com",
      "date_created": "01/01/2024"
    },
    {
      "id": "4",
      "URL": "https://example4.com",
      "date_created": "16/01/2024"
    },
    {
      "id": "5",
      "URL": "https://example5.com",
      "date_created": "12/01/2024"
    }
  ],
  "products": [
    {
      "id": "101",
      "name": "Super product A",
      "description": "This is a brand new product",
      "keywords": [
        "Super",
        "product"
      ],
      "date_created": "18/01/2024"
    },
    {
      "id": "102",
      "name": "Product B",
      "description": "This is a brand new product",
      "keywords": [
        "product",
        "B"
      ],
      "date_created": "18/01/2024"
    },
    {
      "id": "103",
      "name": "TV 4k",
      "description": "This is a brand new product",
      "keywords": [
        "TV", 
        "4k"
      ]
    }
  ]
}